SanctionSightPy/__init__.py
SanctionSightPy/core/__init__.py
SanctionSightPy/core/_rich_.py
SanctionSightPy/core/_table_.py
SanctionSightPy/core/sanction.py
SanctionSightPy/filters/__init__.py
SanctionSightPy/filters/base_filter.py
SanctionSightPy/filters/date_filter.py
SanctionSightPy/filters/entity_filter.py
SanctionSightPy/metadata/__init__.py
SanctionSightPy/metadata/__version__.py
SanctionSightPy/src/__init__.py
SanctionSightPy/src/_client.py
SanctionSightPy/src/_errors.py
SanctionSightPy/src/constants.py
SanctionSightPy/src/logger.py
SanctionSightPy/src/utils.py
SanctionSightPy/utility/__init__.py
SanctionSightPy/utility/_compact_.py
sanctionsightpy-0.4.1.dist-info/LICENSE
sanctionsightpy-0.4.1.dist-info/METADATA
sanctionsightpy-0.4.1.dist-info/WHEEL
sanctionsightpy-0.4.1.dist-info/RECORD
